README.md
setup.py
kuka/__init__.py
kuka/curso.py
kuka/utils.py
kuka_sanchez.egg-info/PKG-INFO
kuka_sanchez.egg-info/SOURCES.txt
kuka_sanchez.egg-info/dependency_links.txt
kuka_sanchez.egg-info/top_level.txt