Metadata-Version: 2.1
Name: kuka-sanchez
Version: 18.1.4
Summary: prueba
Home-page: https://www.mhbol.com
Author: Maximiliano
